CHANGES.txt
LICENSE.txt
MANIFEST.in
README.txt
setup.py
js/__init__.py
js.jqueryui_bootstrap.egg-info/PKG-INFO
js.jqueryui_bootstrap.egg-info/SOURCES.txt
js.jqueryui_bootstrap.egg-info/dependency_links.txt
js.jqueryui_bootstrap.egg-info/entry_points.txt
js.jqueryui_bootstrap.egg-info/namespace_packages.txt
js.jqueryui_bootstrap.egg-info/not-zip-safe
js.jqueryui_bootstrap.egg-info/requires.txt
js.jqueryui_bootstrap.egg-info/top_level.txt
js/jqueryui_bootstrap/__init__.py
js/jqueryui_bootstrap/test_jqueryui_bootstrap.txt
js/jqueryui_bootstrap/resources/jquery-ui.css
js/jqueryui_bootstrap/resources/jquery-ui.ie.css
js/jqueryui_bootstrap/resources/jquery-ui.min.css
js/jqueryui_bootstrap/resources/images/ui-bg_flat_0_aaaaaa_40x100.png
js/jqueryui_bootstrap/resources/images/ui-bg_glass_55_fbf9ee_1x400.png
js/jqueryui_bootstrap/resources/images/ui-bg_glass_65_ffffff_1x400.png
js/jqueryui_bootstrap/resources/images/ui-bg_glass_75_dadada_1x400.png
js/jqueryui_bootstrap/resources/images/ui-bg_glass_75_e6e6e6_1x400.png
js/jqueryui_bootstrap/resources/images/ui-bg_glass_75_ffffff_1x400.png
js/jqueryui_bootstrap/resources/images/ui-bg_highlight-soft_75_cccccc_1x100.png
js/jqueryui_bootstrap/resources/images/ui-bg_inset-soft_95_fef1ec_1x100.png
js/jqueryui_bootstrap/resources/images/ui-icons_222222_256x240.png
js/jqueryui_bootstrap/resources/images/ui-icons_2e83ff_256x240.png
js/jqueryui_bootstrap/resources/images/ui-icons_454545_256x240.png
js/jqueryui_bootstrap/resources/images/ui-icons_888888_256x240.png
js/jqueryui_bootstrap/resources/images/ui-icons_cd0a0a_256x240.png
js/jqueryui_bootstrap/resources/images/ui-icons_f6cf3b_256x240.png