Metadata-Version: 1.0
Name: js.jqueryui-bootstrap
Version: 0.0.0
Summary: fanstatic jQuery UI bootstrap theme.
Home-page: UNKNOWN
Author: Moriyoshi Koizumi
Author-email: mozo@mozo.jp
License: BSD
Platform: UNKNOWN
